[{"Year":1896,"Continent":"Americas","athletes":14,"pct":7.95},{"Year":1896,"Continent":"Europe","athletes":161,"pct":91.48},{"Year":1896,"Continent":"Oceania","athletes":1,"pct":0.57},{"Year":1900,"Continent":"Americas","athletes":90,"pct":7.35},{"Year":1900,"Continent":"Asia","athletes":2,"pct":0.16},{"Year":1900,"Continent":"Europe","athletes":1129,"pct":92.24},{"Year":1900,"Continent":"Oceania","athletes":3,"pct":0.25},{"Year":1904,"Continent":"Africa","athletes":8,"pct":1.23},{"Year":1904,"Continent":"Americas","athletes":584,"pct":89.85},{"Year":1904,"Continent":"Europe","athletes":56,"pct":8.62},{"Year":1904,"Continent":"Oceania","athletes":2,"pct":0.31},{"Year":1906,"Continent":"Africa","athletes":2,"pct":0.24},{"Year":1906,"Continent":"Americas","athletes":41,"pct":4.88},{"Year":1906,"Continent":"Asia","athletes":1,"pct":0.12},{"Year":1906,"Continent":"Europe","athletes":793,"pct":94.29},{"Year":1906,"Continent":"Oceania","athletes":4,"pct":0.48},{"Year":1908,"Continent":"Africa","athletes":14,"pct":0.69},{"Year":1908,"Continent":"Americas","athletes":210,"pct":10.38},{"Year":1908,"Continent":"Europe","athletes":1770,"pct":87.45},{"Year":1908,"Continent":"Oceania","athletes":30,"pct":1.48},{"Year":1912,"Continent":"Africa","athletes":21,"pct":0.87},{"Year":1912,"Continent":"Americas","athletes":225,"pct":9.35},{"Year":1912,"Continent":"Asia","athletes":4,"pct":0.17},{"Year":1912,"Continent":"Europe","athletes":2132,"pct":88.57},{"Year":1912,"Continent":"Oceania","athletes":25,"pct":1.04},{"Year":1920,"Continent":"Africa","athletes":57,"pct":2.13},{"Year":1920,"Continent":"Americas","athletes":362,"pct":13.53},{"Year":1920,"Continent":"Asia","athletes":20,"pct":0.75},{"Year":1920,"Continent":"Europe","athletes":2220,"pct":82.96},{"Year":1920,"Continent":"Oceania","athletes":17,"pct":0.64},{"Year":1924,"Continent":"Africa","athletes":54,"pct":1.66},{"Year":1924,"Continent":"Americas","athletes":527,"pct":16.19},{"Year":1924,"Continent":"Asia","athletes":55,"pct":1.69},{"Year":1924,"Continent":"Europe","athletes":2580,"pct":79.24},{"Year":1924,"Continent":"Oceania","athletes":40,"pct":1.23},{"Year":1928,"Continent":"Africa","athletes":58,"pct":1.79},{"Year":1928,"Continent":"Americas","athletes":519,"pct":15.98},{"Year":1928,"Continent":"Asia","athletes":96,"pct":2.96},{"Year":1928,"Continent":"Europe","athletes":2547,"pct":78.44},{"Year":1928,"Continent":"Oceania","athletes":27,"pct":0.83},{"Year":1932,"Continent":"Africa","athletes":12,"pct":0.62},{"Year":1932,"Continent":"Americas","athletes":756,"pct":39.33},{"Year":1932,"Continent":"Asia","athletes":186,"pct":9.68},{"Year":1932,"Continent":"Europe","athletes":934,"pct":48.6},{"Year":1932,"Continent":"Oceania","athletes":34,"pct":1.77},{"Year":1936,"Continent":"Africa","athletes":85,"pct":1.9},{"Year":1936,"Continent":"Americas","athletes":742,"pct":16.55},{"Year":1936,"Continent":"Asia","athletes":392,"pct":8.74},{"Year":1936,"Continent":"Europe","athletes":3226,"pct":71.94},{"Year":1936,"Continent":"Oceania","athletes":39,"pct":0.87},{"Year":1948,"Continent":"Africa","athletes":120,"pct":2.73},{"Year":1948,"Continent":"Americas","athletes":1044,"pct":23.72},{"Year":1948,"Continent":"Asia","athletes":367,"pct":8.34},{"Year":1948,"Continent":"Europe","athletes":2788,"pct":63.35},{"Year":1948,"Continent":"Oceania","athletes":82,"pct":1.86},{"Year":1952,"Continent":"Africa","athletes":186,"pct":3.78},{"Year":1952,"Continent":"Americas","athletes":913,"pct":18.53},{"Year":1952,"Continent":"Asia","athletes":356,"pct":7.23},{"Year":1952,"Continent":"Europe","athletes":3377,"pct":68.54},{"Year":1952,"Continent":"Oceania","athletes":95,"pct":1.93},{"Year":1956,"Continent":"Africa","athletes":107,"pct":3.24},{"Year":1956,"Continent":"Americas","athletes":666,"pct":20.19},{"Year":1956,"Continent":"Asia","athletes":486,"pct":14.74},{"Year":1956,"Continent":"Europe","athletes":1685,"pct":51.09},{"Year":1956,"Continent":"Oceania","athletes":354,"pct":10.73},{"Year":1960,"Continent":"Africa","athletes":244,"pct":4.56},{"Year":1960,"Continent":"Americas","athletes":827,"pct":15.47},{"Year":1960,"Continent":"Asia","athletes":647,"pct":12.1},{"Year":1960,"Continent":"Europe","athletes":3401,"pct":63.61},{"Year":1960,"Continent":"Oceania","athletes":228,"pct":4.26},{"Year":1964,"Continent":"Africa","athletes":294,"pct":5.72},{"Year":1964,"Continent":"Americas","athletes":949,"pct":18.47},{"Year":1964,"Continent":"Asia","athletes":1011,"pct":19.68},{"Year":1964,"Continent":"Europe","athletes":2576,"pct":50.15},{"Year":1964,"Continent":"Oceania","athletes":307,"pct":5.98},{"Year":1968,"Continent":"Africa","athletes":288,"pct":5.19},{"Year":1968,"Continent":"Americas","athletes":1547,"pct":27.85},{"Year":1968,"Continent":"Asia","athletes":573,"pct":10.32},{"Year":1968,"Continent":"Europe","athletes":2965,"pct":53.38},{"Year":1968,"Continent":"Oceania","athletes":181,"pct":3.26},{"Year":1972,"Continent":"Africa","athletes":458,"pct":6.44},{"Year":1972,"Continent":"Americas","athletes":1454,"pct":20.46},{"Year":1972,"Continent":"Asia","athletes":722,"pct":10.16},{"Year":1972,"Continent":"Europe","athletes":4214,"pct":59.29},{"Year":1972,"Continent":"Oceania","athletes":259,"pct":3.64},{"Year":1976,"Continent":"Africa","athletes":83,"pct":1.37},{"Year":1976,"Continent":"Americas","athletes":1568,"pct":25.84},{"Year":1976,"Continent":"Asia","athletes":664,"pct":10.94},{"Year":1976,"Continent":"Europe","athletes":3486,"pct":57.44},{"Year":1976,"Continent":"Oceania","athletes":268,"pct":4.42},{"Year":1980,"Continent":"Africa","athletes":486,"pct":9.24},{"Year":1980,"Continent":"Americas","athletes":547,"pct":10.4},{"Year":1980,"Continent":"Asia","athletes":423,"pct":8.04},{"Year":1980,"Continent":"Europe","athletes":3679,"pct":69.96},{"Year":1980,"Continent":"Oceania","athletes":124,"pct":2.36},{"Year":1984,"Continent":"Africa","athletes":634,"pct":9.33},{"Year":1984,"Continent":"Americas","athletes":1832,"pct":26.97},{"Year":1984,"Continent":"Asia","athletes":1157,"pct":17.03},{"Year":1984,"Continent":"Europe","athletes":2759,"pct":40.62},{"Year":1984,"Continent":"Oceania","athletes":411,"pct":6.05},{"Year":1988,"Continent":"Africa","athletes":708,"pct":8.38},{"Year":1988,"Continent":"Americas","athletes":1693,"pct":20.04},{"Year":1988,"Continent":"Asia","athletes":1516,"pct":17.95},{"Year":1988,"Continent":"Europe","athletes":4129,"pct":48.89},{"Year":1988,"Continent":"Oceania","athletes":400,"pct":4.74},{"Year":1992,"Continent":"Africa","athletes":743,"pct":7.98},{"Year":1992,"Continent":"Americas","athletes":1935,"pct":20.78},{"Year":1992,"Continent":"Asia","athletes":1404,"pct":15.07},{"Year":1992,"Continent":"Europe","athletes":4769,"pct":51.2},{"Year":1992,"Continent":"Oceania","athletes":463,"pct":4.97},{"Year":1996,"Continent":"Africa","athletes":736,"pct":7.13},{"Year":1996,"Continent":"Americas","athletes":2200,"pct":21.31},{"Year":1996,"Continent":"Asia","athletes":1697,"pct":16.44},{"Year":1996,"Continent":"Europe","athletes":5128,"pct":49.67},{"Year":1996,"Continent":"Oceania","athletes":564,"pct":5.46},{"Year":2000,"Continent":"Africa","athletes":868,"pct":8.17},{"Year":2000,"Continent":"Americas","athletes":2020,"pct":19.0},{"Year":2000,"Continent":"Asia","athletes":1760,"pct":16.56},{"Year":2000,"Continent":"Europe","athletes":5178,"pct":48.72},{"Year":2000,"Continent":"Oceania","athletes":803,"pct":7.55},{"Year":2004,"Continent":"Africa","athletes":814,"pct":7.72},{"Year":2004,"Continent":"Americas","athletes":1951,"pct":18.51},{"Year":2004,"Continent":"Asia","athletes":1877,"pct":17.81},{"Year":2004,"Continent":"Europe","athletes":5239,"pct":49.7},{"Year":2004,"Continent":"Oceania","athletes":660,"pct":6.26},{"Year":2008,"Continent":"Africa","athletes":845,"pct":7.77},{"Year":2008,"Continent":"Americas","athletes":2129,"pct":19.58},{"Year":2008,"Continent":"Asia","athletes":2142,"pct":19.7},{"Year":2008,"Continent":"Europe","athletes":5095,"pct":46.87},{"Year":2008,"Continent":"Oceania","athletes":660,"pct":6.07},{"Year":2012,"Continent":"Africa","athletes":882,"pct":8.41},{"Year":2012,"Continent":"Americas","athletes":2007,"pct":19.14},{"Year":2012,"Continent":"Asia","athletes":1885,"pct":17.97},{"Year":2012,"Continent":"Europe","athletes":5065,"pct":48.3},{"Year":2012,"Continent":"Oceania","athletes":648,"pct":6.18},{"Year":2016,"Continent":"Africa","athletes":990,"pct":8.89},{"Year":2016,"Continent":"Americas","athletes":2522,"pct":22.65},{"Year":2016,"Continent":"Asia","athletes":1989,"pct":17.86},{"Year":2016,"Continent":"Europe","athletes":4906,"pct":44.06},{"Year":2016,"Continent":"Oceania","athletes":727,"pct":6.53}]